topsis/__init__.py
topsis/topsis.py
topsis_ineshkumar_102203363-1.0.4.dist-info/METADATA
topsis_ineshkumar_102203363-1.0.4.dist-info/WHEEL
topsis_ineshkumar_102203363-1.0.4.dist-info/entry_points.txt
topsis_ineshkumar_102203363-1.0.4.dist-info/top_level.txt
topsis_ineshkumar_102203363-1.0.4.dist-info/RECORD
