Metadata-Version: 2.1
Name: topsis_ineshkumar_102203363
Version: 1.0.4
Summary: A Python package to perform TOPSIS (Technique for Order Preference by Similarity to Ideal Solution)
Home-page: https://github.com/inesh126/topsis_ineshkumar_102203363
Author: Inesh Kumar
Author-email: ineshkumar146@gmail.com
Classifier: Programming Language :: Python :: 3
Classifier: License :: OSI Approved :: MIT License
Classifier: Operating System :: OS Independent
Requires-Python: >=3.6
Requires-Dist: numpy
Requires-Dist: pandas
